[
  {
    "id": 1,
    "en": "A little",
    "bn": "খুবই অল্প [বস্তুটি যদি গননা যোগ্য হয় তাইলে A few / few]"
  },
  {
    "id": 2,
    "en": "little",
    "bn": "অল্প কয়েক বা গুটি কয়েক [যদি গননা যোগ্য না হয় তাইলে A little/ little]"
  },
  {
    "id": 3,
    "en": "A few",
    "bn": "অল্প কয়েক বা গুটি কয়েক"
  },
  {
    "id": 4,
    "en": "few",
    "bn": "নাই বললেই চলে"
  },
  {
    "id": 5,
    "en": "Anybody",
    "bn": "যে কেউ"
  },
  {
    "id": 6,
    "en": "According To",
    "bn": "অনুযায়ী"
  },
  {
    "id": 7,
    "en": "All The Same",
    "bn": "একই কথা"
  },
  {
    "id": 8,
    "en": "Anything",
    "bn": "যে কোন কিছু"
  },
  {
    "id": 9,
    "en": "Anywhere",
    "bn": "যে কোনখানে"
  },
  {
    "id": 10,
    "en": "Apparently",
    "bn": "আপাতদৃষ্টিতে"
  },
  {
    "id": 11,
    "en": "At Any Rate",
    "bn": "যাই হোক"
  },
  {
    "id": 12,
    "en": "At Any Time",
    "bn": "যে কোন সময়"
  },
  {
    "id": 13,
    "en": "At Last",
    "bn": "অবশেষে/শেষ পর্যন্ত"
  },
  {
    "id": 14,
    "en": "At Least",
    "bn": "অন্তত - অন্ততঃপক্ষে - কমপক্ষে"
  },
  {
    "id": 15,
    "en": "At Times / off And on",
    "bn": "মাঝে মাঝে"
  },
  {
    "id": 16,
    "en": "Bad",
    "bn": "খারাপ"
  },
  {
    "id": 17,
    "en": "Besides",
    "bn": "তাছাড়া"
  },
  {
    "id": 18,
    "en": "Best",
    "bn": "সব চেয়ে ভাল"
  },
  {
    "id": 19,
    "en": "Better",
    "bn": "আরও ভাল"
  },
  {
    "id": 20,
    "en": "Both",
    "bn": "উভয়"
  },
  {
    "id": 21,
    "en": "By That Time",
    "bn": "ততক্ষনে"
  },
  {
    "id": 22,
    "en": "By The Way",
    "bn": "কথাপ্রসেঙ্গ - প্রসঙ্গক্রমে"
  },
  {
    "id": 23,
    "en": "By Turns",
    "bn": "পর্যায়ক্রমে"
  },
  {
    "id": 24,
    "en": "Comment",
    "bn": "মন্তব্য"
  },
  {
    "id": 25,
    "en": "Comparatively",
    "bn": "তুলনামূলকভাবে"
  },
  {
    "id": 26,
    "en": "Completely",
    "bn": "পুরাপুরি"
  },
  {
    "id": 27,
    "en": "Context",
    "bn": "প্ৰসংগ - প্রসঙ্গ"
  },
  {
    "id": 28,
    "en": "Conversation",
    "bn": "কথাবার্তা"
  },
  {
    "id": 29,
    "en": "End",
    "bn": "শেষ - সমাপ্ত"
  },
  {
    "id": 30,
    "en": "Example",
    "bn": "উদাহরন"
  },
  {
    "id": 31,
    "en": "For",
    "bn": "জন্য"
  },
  {
    "id": 32,
    "en": "For Example",
    "bn": "উদাহরনস্বরূপ"
  },
  {
    "id": 33,
    "en": "From Your Point of View",
    "bn": "আপনার দৃষ্টিতে"
  },
  {
    "id": 34,
    "en": "Good",
    "bn": "ভাল"
  },
  {
    "id": 35,
    "en": "If",
    "bn": "যদি"
  },
  {
    "id": 36,
    "en": "If Not",
    "bn": "যদি না"
  },
  {
    "id": 37,
    "en": "Immediately",
    "bn": "তৎক্ষণাত - তক্ষুনি"
  },
  {
    "id": 38,
    "en": "In A Nutshell / Briefly",
    "bn": "সংক্ষেপে"
  },
  {
    "id": 39,
    "en": "In Accordance with",
    "bn": "অনুসারে"
  },
  {
    "id": 40,
    "en": "In Addition",
    "bn": "অধিকনতু"
  },
  {
    "id": 41,
    "en": "In As Much As / Since",
    "bn": "যেহেতু"
  },
  {
    "id": 42,
    "en": "In Case",
    "bn": "যদি বা"
  },
  {
    "id": 43,
    "en": "In Comparison",
    "bn": "তুলনায়"
  },
  {
    "id": 44,
    "en": "In Spite of",
    "bn": "সত্ত্বেও"
  },
  {
    "id": 45,
    "en": "In Your Opinion",
    "bn": "আপনার মতে"
  },
  {
    "id": 46,
    "en": "Main",
    "bn": "প্রধান - মূল - আসল"
  },
  {
    "id": 47,
    "en": "Mainly",
    "bn": "প্ৰধানতঃ"
  },
  {
    "id": 48,
    "en": "Mainly",
    "bn": "মূলতঃ"
  },
  {
    "id": 49,
    "en": "Majority / Most of",
    "bn": "অধিকাংশ"
  },
  {
    "id": 50,
    "en": "Meanwhile",
    "bn": "মূলতঃ"
  },
  {
    "id": 51,
    "en": "More",
    "bn": "আরও"
  },
  {
    "id": 52,
    "en": "More Or Less / On The Whole",
    "bn": "মোটামুটিভাবে"
  },
  {
    "id": 53,
    "en": "More Than That",
    "bn": "ততোধিক"
  },
  {
    "id": 54,
    "en": "Never",
    "bn": "কখনও না"
  },
  {
    "id": 55,
    "en": "Nevertheless",
    "bn": "তথাপি"
  },
  {
    "id": 56,
    "en": "No More / Not Anymore",
    "bn": "আর না"
  },
  {
    "id": 57,
    "en": "Nobody",
    "bn": "কেউ না"
  },
  {
    "id": 58,
    "en": "Not Yet",
    "bn": "এখনও না"
  },
  {
    "id": 59,
    "en": "Nothing",
    "bn": "কিছু না"
  },
  {
    "id": 60,
    "en": "Now",
    "bn": "এখন"
  },
  {
    "id": 61,
    "en": "Nowhere",
    "bn": "কোথাও না কোন খানে না"
  },
  {
    "id": 62,
    "en": "Often / Frequently",
    "bn": "প্রায় প্রায়ই - ঘন ঘন"
  },
  {
    "id": 63,
    "en": "Opinion",
    "bn": "মতামত – মত"
  },
  {
    "id": 64,
    "en": "Peacefully",
    "bn": "শান্তিপূর্ণভাবে"
  },
  {
    "id": 65,
    "en": "Promise",
    "bn": "কথামত"
  },
  {
    "id": 66,
    "en": "Role",
    "bn": "ভুমিকা"
  },
  {
    "id": 67,
    "en": "Sanction",
    "bn": "বিধিনিষেধ"
  },
  {
    "id": 68,
    "en": "Self-Confidence",
    "bn": "আত্মবিশ্বাস"
  },
  {
    "id": 69,
    "en": "So / Because",
    "bn": "তাই"
  },
  {
    "id": 70,
    "en": "So so",
    "bn": "মোটামুটি"
  },
  {
    "id": 71,
    "en": "Some More",
    "bn": "আর কিছু"
  },
  {
    "id": 72,
    "en": "Somebody",
    "bn": "কেউ"
  },
  {
    "id": 73,
    "en": "Something",
    "bn": "কিছু"
  },
  {
    "id": 74,
    "en": "Sometimes",
    "bn": "কখনও কখনও"
  },
  {
    "id": 75,
    "en": "Somewhere",
    "bn": "কোথাও"
  },
  {
    "id": 76,
    "en": "Statement",
    "bn": "বিবৃতি"
  },
  {
    "id": 77,
    "en": "Sure / of Course",
    "bn": "নিশ্চয়ই"
  },
  {
    "id": 78,
    "en": "Therefore",
    "bn": "সেজন্য"
  },
  {
    "id": 79,
    "en": "To Somebody",
    "bn": "কাউকে"
  },
  {
    "id": 80,
    "en": "Unquestionably",
    "bn": "নিঃসন্দেহে"
  },
  {
    "id": 81,
    "en": "Until Now",
    "bn": "এখন পর্যন্ত"
  },
  {
    "id": 82,
    "en": "Until Now",
    "bn": "এখনও"
  },
  {
    "id": 83,
    "en": "Until Then",
    "bn": "তখন পর্যন্ত"
  },
  {
    "id": 84,
    "en": "Usually",
    "bn": "সাধারনতঃ"
  },
  {
    "id": 85,
    "en": "What Else",
    "bn": "আর কি"
  },
  {
    "id": 86,
    "en": "Whatever",
    "bn": "যা"
  },
  {
    "id": 87,
    "en": "When / Long Ago / At What Time",
    "bn": "কখন"
  },
  {
    "id": 88,
    "en": "Worse",
    "bn": "আরও খারাপ"
  },
  {
    "id": 89,
    "en": "Worst",
    "bn": "সব চেয়ে খারাপ"
  },
  {
    "id": 90,
    "en": "A full bright scholarship",
    "bn": "পূর্ণ মেধাবৃত্তি"
  },
  {
    "id": 91,
    "en": "A goodish steps",
    "bn": "বেশ কানিকটা দূর"
  },
  {
    "id": 92,
    "en": "A mere baby",
    "bn": "একটি কচি খোকা"
  },
  {
    "id": 93,
    "en": "A small fry",
    "bn": "চুনোপুটি"
  },
  {
    "id": 94,
    "en": "Account",
    "bn": "হিসাব দেওয়া/ হিসাব"
  },
  {
    "id": 95,
    "en": "Active",
    "bn": "চঞ্চল"
  },
  {
    "id": 96,
    "en": "Adolescent- Preteen",
    "bn": "কিশোর - কিশোরী"
  },
  {
    "id": 97,
    "en": "Adulterer",
    "bn": "ব্যাভিচারী/ পরস্ত্রীগামী/পরদারগামী"
  },
  {
    "id": 98,
    "en": "Adulterine",
    "bn": "জারজ"
  },
  {
    "id": 99,
    "en": "Age related ailment",
    "bn": "বার্ধক্যজনিত"
  },
  {
    "id": 100,
    "en": "Ahead",
    "bn": "সামনে/সম্মুখে/আগে"
  },
  {
    "id": 101,
    "en": "All contacts",
    "bn": "সকল যোগযোগ"
  },
  {
    "id": 102,
    "en": "All eater",
    "bn": "সর্বভুক"
  },
  {
    "id": 103,
    "en": "Altercate",
    "bn": "কথা কাটা-কাটি করা/কলহ করা"
  },
  {
    "id": 104,
    "en": "Anyway",
    "bn": "যাইহোক"
  },
  {
    "id": 105,
    "en": "Approach",
    "bn": "আগমন করা"
  },
  {
    "id": 106,
    "en": "Arbitrate",
    "bn": "মাতব্বরী করা/মধ্যস্থতা করা"
  },
  {
    "id": 107,
    "en": "Arbitrator",
    "bn": "মাতব্বর"
  },
  {
    "id": 108,
    "en": "Assistance",
    "bn": "সহযোগিতা"
  },
  {
    "id": 109,
    "en": "Atom of truth",
    "bn": "সত্যের লেশ"
  },
  {
    "id": 110,
    "en": "Autopsy",
    "bn": "ময়না তদন্ত"
  },
  {
    "id": 111,
    "en": "Available",
    "bn": "পাওয়া যায়"
  },
  {
    "id": 112,
    "en": "Bad",
    "bn": "খারাপ"
  },
  {
    "id": 113,
    "en": "Baiting nail",
    "bn": "নখ"
  },
  {
    "id": 114,
    "en": "Bathe",
    "bn": "গোসল করা"
  },
  {
    "id": 115,
    "en": "Be excited",
    "bn": "উত্তেজিত হওয়া"
  },
  {
    "id": 116,
    "en": "Be quiet",
    "bn": "শান্ত হও"
  },
  {
    "id": 117,
    "en": "Bear expenses",
    "bn": "খরচ চালানো"
  },
  {
    "id": 118,
    "en": "Beat with shoes",
    "bn": "জুতাপেটা করা"
  },
  {
    "id": 119,
    "en": "Beautiful/Pretty",
    "bn": "সন্দর সুশ্রী"
  },
  {
    "id": 120,
    "en": "Become angry",
    "bn": "রেগে যাওয়া"
  },
  {
    "id": 121,
    "en": "Behavior",
    "bn": "ব্যবহার"
  },
  {
    "id": 122,
    "en": "Beloved",
    "bn": "প্রেমিকা/অত্যাধিক প্রিয়"
  },
  {
    "id": 123,
    "en": "Big/Large",
    "bn": "বড়"
  },
  {
    "id": 124,
    "en": "Blood stained",
    "bn": "রক্তাক্‌ত"
  },
  {
    "id": 125,
    "en": "Boring",
    "bn": "একঘেয়ে"
  },
  {
    "id": 126,
    "en": "Bow down",
    "bn": "নতি স্বীকার করা"
  },
  {
    "id": 127,
    "en": "Breath in",
    "bn": "নিঃশ্বাস নেয়া"
  },
  {
    "id": 128,
    "en": "Breath out",
    "bn": "নিঃশ্বাস ফেলা"
  },
  {
    "id": 129,
    "en": "Bribe",
    "bn": "ঘুষ"
  },
  {
    "id": 130,
    "en": "Broth/gravy",
    "bn": "ঝোল"
  },
  {
    "id": 131,
    "en": "Busy",
    "bn": "বেস্ত"
  },
  {
    "id": 132,
    "en": "By self finance",
    "bn": "নিজ অর্থায়নে"
  },
  {
    "id": 133,
    "en": "Chant slogan",
    "bn": "স্লোগান দেওয়া"
  },
  {
    "id": 134,
    "en": "Character",
    "bn": "চরিত্র"
  },
  {
    "id": 135,
    "en": "Cheat",
    "bn": "প্রতারণা করা/ ঠকানো"
  },
  {
    "id": 136,
    "en": "Chew",
    "bn": "চিবানো"
  },
  {
    "id": 137,
    "en": "Chronologically",
    "bn": "ধারাবহিকভাবে"
  },
  {
    "id": 138,
    "en": "Clean",
    "bn": "পরিষ্কার"
  },
  {
    "id": 139,
    "en": "Climate",
    "bn": "জলবায়ুর"
  },
  {
    "id": 140,
    "en": "Closed from inside",
    "bn": "ভিতর থেকে বন্ধ"
  },
  {
    "id": 141,
    "en": "Cold",
    "bn": "ঠান্ডা"
  },
  {
    "id": 142,
    "en": "Colleagues",
    "bn": "সাহকরমেন"
  },
  {
    "id": 143,
    "en": "Commit nuisance",
    "bn": "মল-মূত্রাদি ত্যাগ করা"
  },
  {
    "id": 144,
    "en": "Comprises Stretches",
    "bn": "বিস্তৃত"
  },
  {
    "id": 145,
    "en": "Conservative",
    "bn": "রক্ষণশীল"
  },
  {
    "id": 146,
    "en": "Constituency",
    "bn": "নির্বাচনী এলাকা"
  },
  {
    "id": 147,
    "en": "Convey",
    "bn": "পৌঁছে দেওয়া/বহন করা"
  },
  {
    "id": 148,
    "en": "Cope with",
    "bn": "কাটিয়ে উঠা"
  },
  {
    "id": 149,
    "en": "Coriander",
    "bn": "ধনিয়া পাতা"
  },
  {
    "id": 150,
    "en": "Cough",
    "bn": "কাশি"
  },
  {
    "id": 151,
    "en": "Create panic",
    "bn": "ত্রাস সৃষ্টি করা"
  },
  {
    "id": 152,
    "en": "Creep",
    "bn": "হামাগুড়ি দেয়া"
  },
  {
    "id": 153,
    "en": "Cross examine",
    "bn": "আসামী/অভিযুক্ত ব্যাক্তি"
  },
  {
    "id": 154,
    "en": "Curable",
    "bn": "আরোগ্যযোগ্য/আরোগ্য হওয়ার"
  },
  {
    "id": 155,
    "en": "Cut joke",
    "bn": "ইয়ার্কি করা"
  },
  {
    "id": 156,
    "en": "Daily",
    "bn": "দৈনিক"
  },
  {
    "id": 157,
    "en": "Daylong",
    "bn": "দিনব্যাপী"
  },
  {
    "id": 158,
    "en": "Deceive",
    "bn": "ফাঁকি দেওয়া/ধোঁকা দেওয়া/ঠকানো"
  },
  {
    "id": 159,
    "en": "Disobey",
    "bn": "আমান্য করা"
  },
  {
    "id": 160,
    "en": "Disrupt/Interrupt",
    "bn": "ব্যাহত করা"
  },
  {
    "id": 161,
    "en": "Dizzy",
    "bn": "মাথা ঘুরা"
  },
  {
    "id": 162,
    "en": "Do a favour",
    "bn": "উপকার করা"
  },
  {
    "id": 163,
    "en": "Dream",
    "bn": "স্বপ্ন"
  },
  {
    "id": 164,
    "en": "Dried chilli",
    "bn": "শুকনা মরিচ"
  },
  {
    "id": 165,
    "en": "Dried fish",
    "bn": "শুটকি মাছ"
  },
  {
    "id": 166,
    "en": "Due money",
    "bn": "পাওনা টাকা"
  },
  {
    "id": 167,
    "en": "Enjoy privilage",
    "bn": "সুযোগ সুবিধা ভোগ করা"
  },
  {
    "id": 168,
    "en": "Earn profit",
    "bn": "মুনাফা অর্জন করা"
  },
  {
    "id": 169,
    "en": "Established",
    "bn": "প্রতিষ্টিত"
  },
  {
    "id": 170,
    "en": "Etc",
    "bn": "ইত্যাদি"
  },
  {
    "id": 171,
    "en": "Even a word",
    "bn": "একটি কথাও"
  },
  {
    "id": 172,
    "en": "Exaggerate",
    "bn": "বাড়াইয়া বাড়াইয়া বলা"
  },
  {
    "id": 173,
    "en": "Expensive",
    "bn": "দামী"
  },
  {
    "id": 174,
    "en": "Extortion",
    "bn": "চাঁদাবাজি"
  },
  {
    "id": 175,
    "en": "False - Lie",
    "bn": "মিথ্যা"
  },
  {
    "id": 176,
    "en": "Fat/Thick",
    "bn": "মোটা"
  },
  {
    "id": 177,
    "en": "Feel shame",
    "bn": "লজ্জা পাওয়া"
  },
  {
    "id": 178,
    "en": "Feel wolf in the stomach",
    "bn": "ক্ষুধায় পেট চো চো করা"
  },
  {
    "id": 179,
    "en": "Fetch",
    "bn": "কোন কিছু গিয়ে নিয়ে আসা"
  },
  {
    "id": 180,
    "en": "File Case",
    "bn": "মামলা দায়ের করা"
  },
  {
    "id": 181,
    "en": "Flatter",
    "bn": "তোষামোদ করা/ ফোলানো/চাটুবাগ করা"
  },
  {
    "id": 182,
    "en": "Flattering policy",
    "bn": "তোষামোদ নীতি"
  },
  {
    "id": 183,
    "en": "Flay",
    "bn": "ছিড়ে ফেলা বা তুলে ফেলা"
  },
  {
    "id": 184,
    "en": "Float",
    "bn": "ভাসা/ভেসে যাওয়া/ভাসানো"
  },
  {
    "id": 185,
    "en": "Floating by the flood water",
    "bn": "বনের জলে ভেসে"
  },
  {
    "id": 186,
    "en": "Fondle",
    "bn": "আদর করা"
  },
  {
    "id": 187,
    "en": "For fear of",
    "bn": "ভয়ে"
  },
  {
    "id": 188,
    "en": "For the sake of",
    "bn": "খাতিরে"
  },
  {
    "id": 189,
    "en": "Fort",
    "bn": "দূর্গ"
  },
  {
    "id": 190,
    "en": "Foul",
    "bn": "বেয়াদব"
  },
  {
    "id": 191,
    "en": "Gargle",
    "bn": "গলা পরিস্কার করা"
  },
  {
    "id": 192,
    "en": "Gentlemanly",
    "bn": "ভদ্রলোক"
  },
  {
    "id": 193,
    "en": "Get married",
    "bn": "বিয়ে করা"
  },
  {
    "id": 194,
    "en": "Get round someone",
    "bn": "কাউকে পটানো"
  },
  {
    "id": 195,
    "en": "Get through",
    "bn": "টেলিফোনে কে পাওয়া"
  },
  {
    "id": 196,
    "en": "Global",
    "bn": "বৈশ্বিক"
  },
  {
    "id": 197,
    "en": "Go away",
    "bn": "চলে যাওয়া"
  },
  {
    "id": 198,
    "en": "Go to bed",
    "bn": "শুতে যাওয়া"
  },
  {
    "id": 199,
    "en": "Go into argument",
    "bn": "তর্কে নামা"
  },
  {
    "id": 200,
    "en": "Go to up stair",
    "bn": "উপর তলায় যাও"
  },
  {
    "id": 201,
    "en": "Goggle at",
    "bn": "চোখ রাঙানো"
  },
  {
    "id": 202,
    "en": "Good",
    "bn": "ভাল"
  },
  {
    "id": 203,
    "en": "Good point",
    "bn": "ভাল কথা"
  },
  {
    "id": 204,
    "en": "Gouge out eyes",
    "bn": "চোখ তুলে ফেলা"
  },
  {
    "id": 205,
    "en": "Grab/Embezzle",
    "bn": "আত্মসাত করা"
  },
  {
    "id": 206,
    "en": "Grave danger",
    "bn": "গুরুতর বিপদ"
  },
  {
    "id": 207,
    "en": "Green chilli",
    "bn": "কাঁচা মরিচ"
  },
  {
    "id": 208,
    "en": "Habit",
    "bn": "স্বভাব"
  },
  {
    "id": 209,
    "en": "Halt",
    "bn": "থামা/বিরতি/দোমনা হওয়া"
  },
  {
    "id": 210,
    "en": "Hamper",
    "bn": "ক্ষতিগ্রস্থ হচ্ছে"
  },
  {
    "id": 211,
    "en": "Hanky panky",
    "bn": "ফাঁকিবাজ"
  },
  {
    "id": 212,
    "en": "Haughtiness",
    "bn": "দেমাগ"
  },
  {
    "id": 213,
    "en": "Have a seat",
    "bn": "আসন লওয়া"
  },
  {
    "id": 214,
    "en": "Hell",
    "bn": "জাহান্নাম/নরক যন্ত্রণা/রসাত"
  },
  {
    "id": 215,
    "en": "Hero",
    "bn": "নাযষ্ঠ নায়কা"
  },
  {
    "id": 216,
    "en": "Hold the line",
    "bn": "লাইনে থাকুন"
  },
  {
    "id": 217,
    "en": "Hot",
    "bn": "গরম"
  },
  {
    "id": 218,
    "en": "Humdrum work",
    "bn": "একঘেয়ে কাজ"
  },
  {
    "id": 219,
    "en": "Ill tempered",
    "bn": "বদমেজাজী"
  },
  {
    "id": 220,
    "en": "Impart",
    "bn": "শিক্ষা দেওয়া"
  },
  {
    "id": 221,
    "en": "Implementation",
    "bn": "বাস্তবায়নে"
  },
  {
    "id": 222,
    "en": "Imposed",
    "bn": "আরোপিত"
  },
  {
    "id": 223,
    "en": "In phases",
    "bn": "র্যায়ক্রমে"
  },
  {
    "id": 224,
    "en": "In true sense",
    "bn": "প্রকৃত অর্থে"
  },
  {
    "id": 225,
    "en": "Increase",
    "bn": "বৃদ্ধি"
  },
  {
    "id": 226,
    "en": "Indebted",
    "bn": "ঋণী"
  },
  {
    "id": 227,
    "en": "Inexpensive",
    "bn": "কম দামী- সস্তা"
  },
  {
    "id": 228,
    "en": "Influence",
    "bn": "প্রভাব"
  },
  {
    "id": 229,
    "en": "Intentionally",
    "bn": "ইচ্ছাকৃতভাবে/উদ্দেশ্য প্রনোদিত"
  },
  {
    "id": 230,
    "en": "Interrupt",
    "bn": "বিগ্ন ঘটানো/ব্যাহত করা/বাধা দেওয়া"
  },
  {
    "id": 231,
    "en": "Intervene",
    "bn": "হস্তক্ষেপ করা/মধ্যবর্তী হওয়া"
  },
  {
    "id": 232,
    "en": "Intimidate",
    "bn": "ভয় দেখানো/ভীতি প্রদর্শন করা"
  },
  {
    "id": 233,
    "en": "Irritant",
    "bn": "উত্তেজক"
  },
  {
    "id": 234,
    "en": "Irritate",
    "bn": "বিরক্ত করা/জ্বালাতন করা"
  },
  {
    "id": 235,
    "en": "It Depends",
    "bn": "হব তা না হলে - হব না হলে"
  },
  {
    "id": 236,
    "en": "Itsy Bitsy",
    "bn": "পিতচি"
  },
  {
    "id": 237,
    "en": "Jest at",
    "bn": "ঠাট্টা করা"
  },
  {
    "id": 238,
    "en": "Jilted lover",
    "bn": "ছ্যাকা খাওয়া প্রেমিকা"
  },
  {
    "id": 239,
    "en": "Just a minute",
    "bn": "একটু সময়"
  },
  {
    "id": 240,
    "en": "Keep confidence",
    "bn": "আস্থা রাখা"
  },
  {
    "id": 241,
    "en": "Keep mum",
    "bn": "একদম চুম থাকা"
  },
  {
    "id": 242,
    "en": "Keep up late",
    "bn": "রাত জাগা"
  },
  {
    "id": 243,
    "en": "Kitchen Market",
    "bn": "কাঁচা বাজার"
  },
  {
    "id": 244,
    "en": "Lame excuse",
    "bn": "বাজে অজুহাত"
  },
  {
    "id": 245,
    "en": "Law and order situation",
    "bn": "আইন শৃঙ্খলা পরিস্থিতি"
  },
  {
    "id": 246,
    "en": "Leak out",
    "bn": "ফাস করে দেওয়া"
  },
  {
    "id": 247,
    "en": "Leave a message",
    "bn": "বার্তা দেওয়া"
  },
  {
    "id": 248,
    "en": "Less/Few",
    "bn": "কম"
  },
  {
    "id": 249,
    "en": "Let down",
    "bn": "কোন কিছু নামানো"
  },
  {
    "id": 250,
    "en": "Look",
    "bn": "তাকানো"
  },
  {
    "id": 251,
    "en": "Loose motions",
    "bn": "পাতলা পায়খানা"
  },
  {
    "id": 252,
    "en": "Lose ground",
    "bn": "পায়ের তলার মাটি সরে যাওয়া"
  },
  {
    "id": 253,
    "en": "Lose heart",
    "bn": "হতাশ হওয়া"
  },
  {
    "id": 254,
    "en": "Lose interest",
    "bn": "উঃসাহ হারিয়ে ফেলা"
  },
  {
    "id": 255,
    "en": "Lose temper",
    "bn": "মাথা খারাপ করা"
  },
  {
    "id": 256,
    "en": "Lucrative offer",
    "bn": "লোভনীয় অফার"
  },

  {
    "id": 258,
    "en": "Mandate",
    "bn": "সনদ"
  },
  {
    "id": 259,
    "en": "Mature/Ripe/Paved",
    "bn": "পাকা"
  },
  {
    "id": 260,
    "en": "Meeting",
    "bn": "বৈঠক - সাক্ষাৎ"
  },
  {
    "id": 261,
    "en": "Members",
    "bn": "সদস্যরা"
  },
  {
    "id": 262,
    "en": "Mild temperature",
    "bn": "হালকা জ্বর"
  },
  {
    "id": 263,
    "en": "Mild",
    "bn": "হালকা/নরম/কোমল/মৃদু বা লঘু"
  },
  {
    "id": 264,
    "en": "Miracle power",
    "bn": "অলৌকিক শক্তি"
  },
  {
    "id": 265,
    "en": "More",
    "bn": "বেশী"
  },
  {
    "id": 266,
    "en": "Mortgage",
    "bn": "বন্ধক দেওয়া"
  },
  {
    "id": 267,
    "en": "Most Foul",
    "bn": "চরম বেয়াদব"
  },
  {
    "id": 268,
    "en": "Moustache",
    "bn": "গোফ/মোচ"
  },
  {
    "id": 269,
    "en": "Move",
    "bn": "নড়া বা নড়ানো/সরা বা সরানো"
  },
  {
    "id": 270,
    "en": "Negative",
    "bn": "নেতিবাচক"
  },
  {
    "id": 271,
    "en": "New",
    "bn": "নুতন"
  },
  {
    "id": 272,
    "en": "Nip",
    "bn": "চিমটি কাটা/ টিপে বা কামড়ে ধরা/ছেঁচা খাওয়া"
  },
  {
    "id": 273,
    "en": "Nipping",
    "bn": "চিমটি"
  },
  {
    "id": 274,
    "en": "Nostalgic",
    "bn": "গৃহকাতুরে"
  },
  {
    "id": 275,
    "en": "Nourish",
    "bn": "প্রশ্রয় দেওয়া/পুষ্টি দিয়ে বড় করা"
  },
  {
    "id": 276,
    "en": "Obscene",
    "bn": "অশ্লীল/খারাপ"
  },
  {
    "id": 277,
    "en": "Oil",
    "bn": "তেল দেয়া"
  },
  {
    "id": 278,
    "en": "Old",
    "bn": "পুরাতন"
  },
  {
    "id": 279,
    "en": "On first-come-fist-serve basis",
    "bn": "আগে আসলে আগে"
  },
  {
    "id": 280,
    "en": "Opportunity",
    "bn": "সুবিধা"
  },
  {
    "id": 281,
    "en": "Order of successions",
    "bn": "পর্যায় গুলো"
  },
  {
    "id": 282,
    "en": "Outsider",
    "bn": "বহিরাগত"
  },
  {
    "id": 283,
    "en": "Pace the music",
    "bn": "ঠেলা সামলানো"
  },
  {
    "id": 284,
    "en": "Peel",
    "bn": "খোসা ছাড়ানো"
  },
  {
    "id": 285,
    "en": "Pedestrian",
    "bn": "পথিক/পথচারি"
  },
  {
    "id": 286,
    "en": "Perspire",
    "bn": "ঘর্মাক্ত হওয়া"
  },
  {
    "id": 287,
    "en": "Pick packet",
    "bn": "পকেট মার"
  },
  {
    "id": 288,
    "en": "Pig",
    "bn": "শুয়োরের বাচ্চা"
  },
  {
    "id": 289,
    "en": "Pilfer",
    "bn": "ছোট খাট চুরি করা"
  },
  {
    "id": 290,
    "en": "Pilferage",
    "bn": "চুরি চামারি"
  },
  {
    "id": 291,
    "en": "Pilferer",
    "bn": "ছিচকে চোর/ছোটখাট চুরি করে যে"
  },
  {
    "id": 292,
    "en": "Pinch",
    "bn": "নখ দিয়া খামটি দেয়া"
  },
  {
    "id": 293,
    "en": "Play neutral rule",
    "bn": "নিরপেক্ষ ভূমিকা রাখা"
  },
  {
    "id": 294,
    "en": "Poke nose",
    "bn": "নাক গলানো"
  },
  {
    "id": 295,
    "en": "Population",
    "bn": "জনসংখ্যা - লোকসংখ্যা"
  },
  {
    "id": 296,
    "en": "Pork",
    "bn": "শুকরের মাংস"
  },
  {
    "id": 297,
    "en": "Positive",
    "bn": "ইতিবাচক"
  },
  {
    "id": 298,
    "en": "Praise",
    "bn": "প্রশংসা করা"
  },
  {
    "id": 299,
    "en": "Prescribe",
    "bn": "ব্যবস্থাপত্র দেওয়া"
  },
  {
    "id": 300,
    "en": "Price hike",
    "bn": "মূল্য বৃদ্ধি"
  },
  {
    "id": 301,
    "en": "Principal",
    "bn": "সদর"
  },
  {
    "id": 302,
    "en": "Procession",
    "bn": "মিছিল/শোভাযাত্রা"
  },
  {
    "id": 303,
    "en": "Prohibited",
    "bn": "নিষিদ্ধ"
  },
  {
    "id": 304,
    "en": "Prosperous",
    "bn": "সমৃদ্ধ"
  },
  {
    "id": 305,
    "en": "Punch",
    "bn": "ঘুষি মারা"
  },
  {
    "id": 306,
    "en": "Puppy",
    "bn": "কুত্তার বাচ্চা"
  },
  {
    "id": 307,
    "en": "Put It In Writing / On The Record",
    "bn": "কাগজে কলমে"
  },
  {
    "id": 308,
    "en": "Racism",
    "bn": "জাতি বিদ্বেষ"
  },
  {
    "id": 309,
    "en": "Raw/Unripe/Unpaved",
    "bn": "কাঁচা"
  },
  {
    "id": 310,
    "en": "Reach",
    "bn": "পৌঁছানো/নাগাল পাওয়া পারা"
  },
  {
    "id": 311,
    "en": "Really Picky",
    "bn": "খুঁত খুঁতি"
  },
  {
    "id": 312,
    "en": "Relationship",
    "bn": "সম্পর্ক"
  },
  {
    "id": 313,
    "en": "Release",
    "bn": "জেড়ে/অব্যাহতি/মুক্তি দেওয়া"
  },
  {
    "id": 314,
    "en": "Remain alert",
    "bn": "সতর্ক থাকা"
  },
  {
    "id": 315,
    "en": "Repeat",
    "bn": "পুনরায় বলা"
  },
  {
    "id": 316,
    "en": "Respiratory problem",
    "bn": "শ্বাসকষ্ট"
  },
  {
    "id": 317,
    "en": "Roam",
    "bn": "ঘুরে বেড়ানো"
  },
  {
    "id": 318,
    "en": "Running away",
    "bn": "পালিয়ে যাচ্ছে"
  },
  {
    "id": 319,
    "en": "Scold",
    "bn": "গলামন্দ করা"
  },
  {
    "id": 320,
    "en": "Scratch",
    "bn": "চুলকানো"
  },
  {
    "id": 321,
    "en": "Scratching nose",
    "bn": "নাক চুলকানো"
  },
  {
    "id": 322,
    "en": "Seize",
    "bn": "আটক করা"
  },
  {
    "id": 323,
    "en": "Separate",
    "bn": "পৃথক"
  },
  {
    "id": 324,
    "en": "Severe cold",
    "bn": "প্রচন্ড ঠান্ডা"
  },
  {
    "id": 325,
    "en": "Shaven",
    "bn": "কামানো"
  },
  {
    "id": 326,
    "en": "Shiver",
    "bn": "কাঁপা/ঠান্ডায় বা ভয়ে থরথর করে কাঁপা"
  },
  {
    "id": 327,
    "en": "Short lived",
    "bn": "স্বল্পায়ু"
  },
  {
    "id": 328,
    "en": "Short tempered",
    "bn": "রগচটা"
  },
  {
    "id": 329,
    "en": "Siblings",
    "bn": "ভাই-বোন"
  },
  {
    "id": 330,
    "en": "Situated",
    "bn": "অবস্থিত"
  },
  {
    "id": 331,
    "en": "Slap",
    "bn": "থাপ্পর মারা"
  },
  {
    "id": 332,
    "en": "Sleep",
    "bn": "ঘুমানো"
  },
  {
    "id": 333,
    "en": "Slightest provocation",
    "bn": "স্বল্প উত্তেজনায়"
  },
  {
    "id": 334,
    "en": "Small",
    "bn": "ছোট"
  },
  {
    "id": 335,
    "en": "Smallest",
    "bn": "ক্ষুদ্রতম"
  },
  {
    "id": 336,
    "en": "Smell",
    "bn": "ঘ্রাণ নেওয়া"
  },
  {
    "id": 337,
    "en": "Snatch away",
    "bn": "ছিনিয়ে ছোট"
  },
  {
    "id": 338,
    "en": "Snatcher",
    "bn": "ছিনতাইকারী"
  },
  {
    "id": 339,
    "en": "Snatching",
    "bn": "ছিনতাই"
  },
  {
    "id": 340,
    "en": "Sneeze",
    "bn": "হাঁচি দেওয়া"
  },
  {
    "id": 341,
    "en": "So crowded",
    "bn": "খুব বেশি ভিড়"
  },
  {
    "id": 342,
    "en": "Solution",
    "bn": "সমাধান"
  },
  {
    "id": 343,
    "en": "Son of bitch",
    "bn": "কুত্তার বাচ্চা"
  },
  {
    "id": 344,
    "en": "Sore-throat",
    "bn": "গলা ব্যাথা"
  },
  {
    "id": 345,
    "en": "Special",
    "bn": "বিশেষ"
  },
  {
    "id": 346,
    "en": "Spoiled boy",
    "bn": "নষ্ট/বখাটে ছেলে"
  },
  {
    "id": 347,
    "en": "Sprinkle",
    "bn": "পানি ছিটিয়ে দেয়া"
  },
  {
    "id": 348,
    "en": "Squat",
    "bn": "উবু হয়ে দেয়া"
  },
  {
    "id": 349,
    "en": "Stampede",
    "bn": "পায়ে পাড়া দেওয়া/ছত্রভঙ্গ করা"
  },
  {
    "id": 350,
    "en": "Stretch",
    "bn": "বাড়ানো/এগিয়ে দেওয়া"
  },
  {
    "id": 351,
    "en": "Success",
    "bn": "সাফল্যে"
  },
  {
    "id": 352,
    "en": "Success",
    "bn": "সাফল্যে"
  },
  {
    "id": 353,
    "en": "Suck",
    "bn": "চোষা"
  },
  {
    "id": 354,
    "en": "Swallow",
    "bn": "গিলে ফেলা"
  },
  {
    "id": 355,
    "en": "Take Account",
    "bn": "হিসাব নেওয়া"
  },
  {
    "id": 356,
    "en": "Take aside",
    "bn": "সরিয়ে নেওয়া"
  },
  {
    "id": 357,
    "en": "Take medicine",
    "bn": "ওষুধ খাওয়া"
  },
  {
    "id": 358,
    "en": "Take photograph",
    "bn": "ছবি তোলা"
  },
  {
    "id": 359,
    "en": "Take revenge",
    "bn": "প্রতিশোধ লওয়া"
  },
  {
    "id": 360,
    "en": "Take stringent action",
    "bn": "কঠোর পদক্ষেপ নেওয়া"
  },
  {
    "id": 361,
    "en": "Tap",
    "bn": "টোকা দেওয়া/চাপড় দেওয়া/টোক/চাপড়"
  },
  {
    "id": 362,
    "en": "Tapping teeth",
    "bn": "দাঁত ঢোকানো"
  },
  {
    "id": 363,
    "en": "Tell a lie",
    "bn": "মিথ্যা বলা"
  },
  {
    "id": 364,
    "en": "Temper",
    "bn": "মেজাজ"
  },
  {
    "id": 365,
    "en": "The root of all spoil",
    "bn": "সব নষ্টের গোড়া"
  },
  {
    "id": 366,
    "en": "The whole day",
    "bn": "সারাদিন"
  },
  {
    "id": 367,
    "en": "Thin",
    "bn": "রোগা"
  },
  {
    "id": 368,
    "en": "Threat to kill",
    "bn": "হত্যার হুমকি দেওয়া"
  },
  {
    "id": 369,
    "en": "Tolerable",
    "bn": "সহনীয়/সহ্য করা যায়"
  },
  {
    "id": 370,
    "en": "Towel",
    "bn": "তোয়ালে"
  },
  {
    "id": 371,
    "en": "Tremble",
    "bn": "কেপেঁ ওঠা"
  },
  {
    "id": 372,
    "en": "Turn a some",
    "bn": "ডিগবাজি খাওয়া"
  },
  {
    "id": 373,
    "en": "Turn right",
    "bn": "ডানে মোড় নেওয়া"
  },
  {
    "id": 374,
    "en": "Ugly",
    "bn": "কুৎসিত - জঘন্য - বিশ্রী"
  },
  {
    "id": 375,
    "en": "Ulterior motive",
    "bn": "অসৎ উদ্দেশ্য"
  },
  {
    "id": 376,
    "en": "Uneven and jerky",
    "bn": "ভাঙ্গাচোরা"
  },
  {
    "id": 377,
    "en": "Ungentlemanly",
    "bn": "অভদ্রলোক"
  },
  {
    "id": 378,
    "en": "Unlock",
    "bn": "খুলে দেওয়া"
  },
  {
    "id": 379,

    "en": "Utter",
    "bn": "উচ্চারণ করা"
  },
  {
    "id": 380,
    "en": "Vegetarian",
    "bn": "নিরামিষভোজী"
  },
  {
    "id": 381,
    "en": "Village arbitrator",
    "bn": "গ্রাম্য মাতব্বর"
  },
  {
    "id": 382,
    "en": "Vocal",
    "bn": "প্রতিবাদী/সোচ্চার"
  },
  {
    "id": 383,
    "en": "Vomit",
    "bn": "বমি করা/উদগীরণ করা"
  },
  {
    "id": 384,
    "en": "Vote for",
    "bn": "ভোট দেওয়া"
  },
  {
    "id": 385,
    "en": "Vote Rigging",
    "bn": "ভোট কারচুপি"
  },
  {
    "id": 386,
    "en": "Walk about",
    "bn": "হেঁটে বেড়ানো"
  },
  {
    "id": 387,
    "en": "Walk",
    "bn": "হাটা"
  },
  {
    "id": 388,
    "en": "Wane",
    "bn": "ক্রমশ হ্রাস পাওয়া কমে যাওয়া"
  },
  {
    "id": 389,
    "en": "Warm",
    "bn": "সতর্ক করে দেয়া"
  },
  {
    "id": 390,
    "en": "Watch",
    "bn": "কোন কিছু দেখা"
  },
  {
    "id": 391,
    "en": "weal",
    "bn": "ভাল/কল্যাণ"
  },
  {
    "id": 392,
    "en": "Wear beard",
    "bn": "দাড়ি রাখা"
  },
  {
    "id": 393,
    "en": "Whimper",
    "bn": "ঘ্যান ঘ্যান করা"
  },
  {
    "id": 394,
    "en": "Window curtain",
    "bn": "জানালা পর্দা"
  },
  {
    "id": 395,
    "en": "Wipe",
    "bn": "মুছা/কাপড়/কাগজ/হাত ইত্যাদি দিয়ে মুছে পরিষ্কার করা"
  },
  {
    "id": 396,
    "en": "Without delay",
    "bn": "আনতিবিলম্বে"
  },
  {
    "id": 397,
    "en": "Worm eaten",
    "bn": "পোকায় খাওয়া"
  },
  {
    "id": 398,
    "en": "Wound",
    "bn": "আহত করা"
  },
  {
    "id": 399,
    "en": "Young",
    "bn": "অল্পবয়স্ক"
  },
  {
    "id": 400,
    "en": "Young devil",
    "bn": "শয়তানের বাচ্চা"
  }
]
